defensio
