Metadata-Version: 1.0
Name: defensio
Version: 0.9.1
Summary: Official Python library for Defensio 2.0
Home-page: http://github.com/defensio/defensio-python
Author: Camilo Lopez
Author-email: clopez@websense.com
License: MIT
Keywords: defensio spam antispam api
Platform: UNKNOWN
Classifier: License :: OSI Approved :: MIT License
Classifier: Programming Language :: Python
Classifier: Development Status :: 4 - Beta
Classifier: Intended Audience :: Developers
Classifier: Topic :: Internet
